README
setup.py
bin/testprint.py
dungeon/__init__.py
dungeon/printlist.py
dungeon.egg-info/PKG-INFO
dungeon.egg-info/SOURCES.txt
dungeon.egg-info/dependency_links.txt
dungeon.egg-info/requires.txt
dungeon.egg-info/top_level.txt