Metadata-Version: 1.0
Name: dungeon
Version: 0.1
Summary: Dungeon of Crow
Home-page: just local
Author: Nicolas tarral
Author-email: nicolas@tarral.net
License: UNKNOWN
Download-URL: local
Platform: UNKNOWN
